<?xml version="1.0" encoding="UTF-8"?>
<creation>
<service>
<nom-abrege>INFO</nom-abrege>
<employe>
<matricule>1515</matricule>
<nom>Marignan</nom>
<prenom>Pierre</prenom>
<telephone-fixe>0155447788</telephone-fixe>
<telephone-mobile>0699887711</telephone-mobile>
<courriel>marignan.pierre@lapie.fr</courriel>
<responsable>true</responsable>
<poste>CADRE</poste>
</employe>
<employe>
<matricule>2001</matricule>
<nom>Odyssée</nom>
<prenom>Stanley</prenom>
<telephone-fixe>0144667788</telephone-fixe>
<telephone-mobile>0633887711</telephone-mobile>
<courriel>odyssee.stan@lapie.fr</courriel>
<poste>TECHNICIEN</poste>
</employe>
</service>
<service>
<nom-abrege>DRH</nom-abrege>
<employe>
<matricule>3012</matricule>
<nom>Dupont</nom>
<prenom>Isabelle</prenom>
<telephone-fixe>0144779922</telephone-fixe>
<telephone-mobile>0633112277</telephone-mobile>
<courriel>dupont.isabelle@lapie.fr</courriel>
<responsable>true</responsable>
<poste>EMPLOYE</poste>
</employe>
</service>
<service>
<nom-abrege>COMPTA</nom-abrege>
<employe>
<matricule>66666</matricule>
<nom>Durand</nom>
<prenom>Gabrielle</prenom>
<telephone-fixe>0166334411</telephone-fixe>
<telephone-mobile>0666334411</telephone-mobile>
<courriel>durand.gaby@lapie.fr</courriel>
<responsable>true</responsable>
<poste>CADRE</poste>
</employe>
<employe>
<matricule>77777</matricule>
<nom>Abel</nom>
<prenom>Maurice</prenom>
<telephone-fixe>0167334411</telephone-fixe>
<telephone-mobile>0676334411</telephone-mobile>
<courriel>abel.maurice@lapie.fr</courriel>
<poste>EMPLOYE</poste>
</employe>
</service>
</creation>